scubaduck/__init__.py
scubaduck/sample.csv
scubaduck/server.py
scubaduck/static/index.html
scubaduck/static/js/chip_input.js
scubaduck/static/js/sidebar.js
scubaduck/static/js/table_view.js
scubaduck/static/js/time_column.js
scubaduck/static/js/timeseries_chart.js
scubaduck/static/js/view_settings.js
scubaduck-0.1.0.dist-info/METADATA
scubaduck-0.1.0.dist-info/WHEEL
scubaduck-0.1.0.dist-info/RECORD
