Metadata-Version: 2.4
Name: scubaduck
Version: 0.1.0
Summary: Scuba on DuckDB
License: MIT
Requires-Python: >=3.12
Requires-Dist: duckdb
Requires-Dist: flask
Requires-Dist: python-dateutil>=2.9.0.post0
